Metadata-Version: 1.0
Name: openid-mongodb
Version: 0.1
Summary: A MongoDb storage backend for the python-openid package
Home-page: http://github.com/arielbackenroth/openid-mongodb
Author: Ariel Backenroth
Author-email: arielb@alumni.rice.edu
License: MIT
Keywords: openid mongodb
Platform: UNKNOWN
Classifier: Development Status :: 4 - Beta
Classifier: Intended Audience :: Developers
Classifier: License :: OSI Approved :: MIT License
Classifier: Topic :: Internet :: WWW/HTTP
